MANIFEST.in
README.md
README.rst
setup.cfg
setup.py
kaizen/__init__.py
kaizen/api.py
kaizen/client.py
kaizen/request.py
kaizen.egg-info/PKG-INFO
kaizen.egg-info/SOURCES.txt
kaizen.egg-info/dependency_links.txt
kaizen.egg-info/requires.txt
kaizen.egg-info/top_level.txt
test/test_api.py
test/test_client.py
test/test_request.py