Metadata-Version: 1.1
Name: kaizen
Version: 0.1.4
Summary: A python client and cli to manage your projects on AgileZen Kanban style.
Home-page: https://github.com/bertrandvidal/kaizen
Author: Bertrand Vidal
Author-email: vidal.bertrand@gmail.com
License: UNKNOWN
Download-URL: https://pypi.python.org/pypi/kaizen
Platform: UNKNOWN
Classifier: Environment :: Console
Classifier: Intended Audience :: Developers
Classifier: Intended Audience :: Information Technology
Classifier: Operating System :: OS Independent
Classifier: Programming Language :: Python
